kidsafeinternet/__init__.py
kidsafeinternet/detector.py
kidsafeinternet-0.0.1.dist-info/LICENSE
kidsafeinternet-0.0.1.dist-info/METADATA
kidsafeinternet-0.0.1.dist-info/WHEEL
kidsafeinternet-0.0.1.dist-info/top_level.txt
kidsafeinternet-0.0.1.dist-info/RECORD
